Metadata-Version: 2.1
Name: pyopenset
Version: 0.0.12
Summary: Infering novel classes for classification problems
Home-page: https://github.com/R-S-P-MODELS/pyopenset/
Author: Rafael S. Pereira
Author-email: r.s.p.models@gmail.com
License: UNKNOWN
Platform: UNKNOWN
Classifier: Programming Language :: Python :: 3
Classifier: License :: OSI Approved :: GNU General Public License (GPL)
Classifier: Operating System :: OS Independent
Requires-Python: >=3.5
